layer_peel/__init__.py
layer_peel/cli.py
layer_peel/exceptions.py
layer_peel/iter_unpack.py
layer_peel/types.py
layer_peel/utils.py
layer_peel/ct/__init__.py
layer_peel/ct/py7z.py
layer_peel/ct/rar.py
layer_peel/ct/tar.py
layer_peel/ct/tgz.py
layer_peel/ct/zip.py
layer_peel-0.1.0.dist-info/METADATA
layer_peel-0.1.0.dist-info/WHEEL
layer_peel-0.1.0.dist-info/entry_points.txt
layer_peel-0.1.0.dist-info/licenses/LICENSE
layer_peel-0.1.0.dist-info/RECORD
