Metadata-Version: 2.4
Name: layer-peel
Version: 0.1.0
Summary: 一个用于递归解压缩多层嵌套压缩文件的Python库
Project-URL: Homepage, https://github.com/yourusername/layer-peel
Project-URL: Documentation, https://layer-peel.readthedocs.io/
Project-URL: Repository, https://github.com/yourusername/layer-peel.git
Project-URL: Bug Tracker, https://github.com/yourusername/layer-peel/issues
Project-URL: Changelog, https://github.com/yourusername/layer-peel/blob/main/CHANGELOG.md
Author: Layer Peel Contributors
Maintainer: Layer Peel Contributors
License: MIT License
License-File: LICENSE
Keywords: 7z,archive,compression,extraction,nested,rar,recursive,tar,zip
Classifier: Development Status :: 4 - Beta
Classifier: Intended Audience :: Developers
Classifier: License :: OSI Approved :: MIT License
Classifier: Operating System :: OS Independent
Classifier: Programming Language :: Python :: 3
Classifier: Programming Language :: Python :: 3.10
Classifier: Programming Language :: Python :: 3.11
Classifier: Programming Language :: Python :: 3.12
Classifier: Topic :: Software Development :: Libraries :: Python Modules
Classifier: Topic :: System :: Archiving :: Compression
Classifier: Topic :: Utilities
Requires-Python: >=3.10
Requires-Dist: chardet>=5.2.0
Requires-Dist: py7zr>=1.0.0
Requires-Dist: python-magic-bin>=0.4.14; sys_platform == 'win32'
Requires-Dist: python-magic>=0.4.27; sys_platform != 'win32'
Requires-Dist: rarfile>=4.2
Requires-Dist: stream-unzip>=0.0.99
Provides-Extra: dev
Requires-Dist: mypy>=1.0.0; extra == 'dev'
Requires-Dist: pre-commit>=3.0.0; extra == 'dev'
Requires-Dist: pytest-cov>=4.0.0; extra == 'dev'
Requires-Dist: pytest>=7.0.0; extra == 'dev'
Requires-Dist: ruff>=0.1.0; extra == 'dev'
Provides-Extra: docs
Requires-Dist: myst-parser>=1.0.0; extra == 'docs'
Requires-Dist: sphinx-rtd-theme>=1.2.0; extra == 'docs'
Requires-Dist: sphinx>=6.0.0; extra == 'docs'
Provides-Extra: test
Requires-Dist: pytest-cov>=4.0.0; extra == 'test'
Requires-Dist: pytest-mock>=3.10.0; extra == 'test'
Requires-Dist: pytest>=7.0.0; extra == 'test'
